db_copilot/__init__.py
db_copilot/chat.py
db_copilot/follow_up.py
db_copilot/lib.py
db_copilot/llm.py
db_copilot/memory_manager.py
db_copilot/obfuscator
db_copilot/obfuscator.exe
db_copilot/planner.py
db_copilot/planner.py.encode
db_copilot/suggestion.py
db_copilot/tool.py
db_copilot/analysis/__init__.py
db_copilot/analysis/analysis_com.py
db_copilot/analysis/analysis_tool.py
db_copilot/analysis/auto_analyzer.py
db_copilot/analysis/ols_analyzer.py
db_copilot/contract/__init__.py
db_copilot/contract/api_core.py
db_copilot/contract/chat_core.py
db_copilot/contract/data_core.py
db_copilot/contract/db_core.py
db_copilot/contract/db_provider.py
db_copilot/contract/embedding_core.py
db_copilot/contract/generic.py
db_copilot/contract/knowledge_core.py
db_copilot/contract/llm_core.py
db_copilot/contract/memory_core.py
db_copilot/contract/plan_core.py
db_copilot/contract/tool_core.py
db_copilot/contract/utils/__init__.py
db_copilot/contract/utils/lru.py
db_copilot/contract/utils/misc_utils.py
db_copilot/contract/utils/text_utils.py
db_copilot/db_provider/__init__.py
db_copilot/db_provider/azureml_endpoint.py
db_copilot/db_provider/db_provider_api.py
db_copilot/db_provider/db_provider_client.py
db_copilot/db_provider/db_provider_config.py
db_copilot/db_provider/db_provider_pool.py
db_copilot/db_provider/db_provider_service.py
db_copilot/db_provider/cli/__init__.py
db_copilot/db_provider/cli/deploy_endpoint.py
db_copilot/db_provider/db_executor/__init__.py
db_copilot/db_provider/db_executor/clickhouse_executor.py
db_copilot/db_provider/db_executor/cosmos_executor.py
db_copilot/db_provider/db_executor/db_executor.py
db_copilot/db_provider/db_executor/kusto_executor.py
db_copilot/db_provider/db_executor/sheet_file_executor.py
db_copilot/db_provider/db_executor/sql_server_executor.py
db_copilot/db_provider/db_executor/sql_utils.py
db_copilot/db_provider/db_executor/sqlite_executor.py
db_copilot/db_provider/db_executor/contrib/__init__.py
db_copilot_tool-0.0.8.dist-info/METADATA
db_copilot_tool-0.0.8.dist-info/WHEEL
db_copilot_tool-0.0.8.dist-info/entry_points.txt
db_copilot_tool-0.0.8.dist-info/top_level.txt
db_copilot_tool-0.0.8.dist-info/RECORD
