Metadata-Version: 2.1
Name: db_copilot_tool
Version: 0.0.8
Summary: nl2sql tool for prompt flow
Author: Microsoft Corporation
Author-email: xiangrao@microsoft.com
Classifier: Intended Audience :: Developers
Classifier: Programming Language :: Python :: 3.8
Classifier: Programming Language :: Python :: 3.9
Requires-Python: >=3.8
Requires-Dist: Pympler <2.0.0,>=1.0.1
Requires-Dist: azure-storage-blob <13.0.0,>=12.16.0
Requires-Dist: backoff <3.0.0,>=2.2.1
Requires-Dist: emoji <2.0.0,>=1.7.0
Requires-Dist: faiss-cpu <2.0.0,>=1.7.3
Requires-Dist: filelock <4.0.0,>=3.11.0
Requires-Dist: huggingface-hub <0.22.0,>=0.21.1
Requires-Dist: openai >=1.12.0
Requires-Dist: opencensus-ext-azure <2.0.0,>=1.1.9
Requires-Dist: pandas <2.0.0,>=1.5.3
Requires-Dist: protobuf <5.0.0,>=4.22.0
Requires-Dist: pyodbc <5.0.0,>=4.0.35
Requires-Dist: requests <3.0.0,>=2.27.1
Requires-Dist: sqlparse <0.5.0,>=0.4.4
Requires-Dist: tabulate <0.10.0,>=0.9.0
Requires-Dist: tqdm <5.0.0,>=4.63.0
Requires-Dist: diskcache
Requires-Dist: azureml-core
Requires-Dist: retrying
Requires-Dist: azureml-telemetry
